{
  "required": true,
  "minVersion": "0.8",
  "package": "to_binio.useful_brush.mixin",
  "compatibilityLevel": "JAVA_17",
  "mixins": [
    "BrushItemMixin",
    "BrushItemInvoker",
    "entity.sheep.SheepBrushableMixin",
    "entity.sheep.SheepBrushCountMixin",
    "entity.sheep.SheepMixin",
    "entity.sheep.SheepAccessor",
    "entity.chicken.ChickenBrushableMixin",
    "entity.chicken.ChickenBrushCountMixin",
    "entity.chicken.ChickenMixin",
    "entity.wolf.WolfBrushableMixin",
    "entity.wolf.WolfMixin",
    "block.CampfireMixin",
    "ItemMixin"
  ],
  "client": [
  ],
  "injectors": {
    "defaultRequire": 1
  }
}
